pgn.py
setup.py
pgnparser.egg-info/PKG-INFO
pgnparser.egg-info/SOURCES.txt
pgnparser.egg-info/dependency_links.txt
pgnparser.egg-info/top_level.txt