Metadata-Version: 1.0
Name: pgnparser
Version: 1.0
Summary: A python PGN parser
Home-page: http://renatopp.com/pgnparser
Author: Renato de Pontes Pereira
Author-email: renato.ppontes@gmail.com
License: MIT License
Download-URL: https://github.com/renatopp/pgnparser
Keywords: chess game pgn parser python
Platform: UNKNOWN
Classifier: Development Status :: 5 - Production/Stable
Classifier: Environment :: MacOS X
Classifier: Environment :: Win32 (MS Windows)
Classifier: Environment :: X11 Applications
Classifier: Intended Audience :: Developers
Classifier: License :: OSI Approved :: MIT License
Classifier: Natural Language :: English
Classifier: Operating System :: MacOS :: MacOS X
Classifier: Operating System :: Microsoft :: Windows
Classifier: Operating System :: POSIX :: Linux
Classifier: Programming Language :: Python
Classifier: Topic :: Software Development :: Libraries :: Python Modules
Classifier: Topic :: Games/Entertainment
